sihl/__init__.py
sihl/lightning_module.py
sihl/sihl_model.py
sihl/timm_backbone.py
sihl/torchvision_backbone.py
sihl/heads/README.md
sihl/heads/__init__.py
sihl/heads/anomaly_detection.py
sihl/heads/autoencoding.py
sihl/heads/autoregressive_text_recognition.py
sihl/heads/depth_estimation.py
sihl/heads/instance_segmentation.py
sihl/heads/keypoint_detection.py
sihl/heads/metric_learning.py
sihl/heads/multiclass_classification.py
sihl/heads/multilabel_classification.py
sihl/heads/object_detection.py
sihl/heads/panoptic_segmentation.py
sihl/heads/quadrilateral_detection.py
sihl/heads/regression.py
sihl/heads/scene_text_recognition.py
sihl/heads/semantic_segmentation.py
sihl/heads/view_invariance_learning.py
sihl/layers/__init__.py
sihl/layers/attention.py
sihl/layers/bifpn.py
sihl/layers/convblocks.py
sihl/layers/fpn.py
sihl/layers/pooling.py
sihl/layers/preprocessing.py
sihl/layers/scalers.py
sihl/utils/__init__.py
sihl/utils/polygon_iou.py
sihl/visualization/__init__.py
sihl/visualization/anomaly_detection.py
sihl/visualization/autoencoding.py
sihl/visualization/autoregressive_text_recognition.py
sihl/visualization/common.py
sihl/visualization/depth_estimation.py
sihl/visualization/instance_segmentation.py
sihl/visualization/keypoint_detection.py
sihl/visualization/metric_learning.py
sihl/visualization/multiclass_classification.py
sihl/visualization/multilabel_classification.py
sihl/visualization/object_detection.py
sihl/visualization/panoptic_segmentation.py
sihl/visualization/quadrilateral_detection.py
sihl/visualization/regression.py
sihl/visualization/scene_text_recognition.py
sihl/visualization/semantic_segmentation.py
sihl/visualization/view_invariance_learning.py
sihl-0.0.3.post7.dist-info/METADATA
sihl-0.0.3.post7.dist-info/WHEEL
sihl-0.0.3.post7.dist-info/licenses/LICENSE
sihl-0.0.3.post7.dist-info/RECORD
