Metadata-Version: 2.3
Name: sihl
Version: 0.0.3.post7
Summary: Simple Image Heads and Layers
Project-URL: Homepage, https://github.com/jonregef/sihl
Project-URL: Repository, https://github.com/jonregef/sihl
Author-email: Jon <jon@sihl.ai>
License: Apache-2.0
Classifier: Development Status :: 4 - Beta
Classifier: Intended Audience :: Developers
Classifier: Intended Audience :: Education
Classifier: Intended Audience :: Science/Research
Classifier: License :: OSI Approved :: Apache Software License
Classifier: Operating System :: OS Independent
Classifier: Programming Language :: Python :: 3.9
Classifier: Programming Language :: Python :: 3.10
Classifier: Programming Language :: Python :: 3.11
Classifier: Programming Language :: Python :: 3.12
Classifier: Topic :: Scientific/Engineering :: Artificial Intelligence
Requires-Python: >=3.9
Requires-Dist: einops>=0.8.0
Requires-Dist: faster-coco-eval>=1.6.5
Requires-Dist: matplotlib>=3.10.0
Requires-Dist: torch>=2.5.1
Requires-Dist: torchmetrics>=1.6.0
Requires-Dist: torchvision>=0.20.1
Provides-Extra: all
Requires-Dist: lightning>=2.4.0; extra == 'all'
Requires-Dist: onnx>=1.17.0; extra == 'all'
Requires-Dist: onnxruntime>=1.19.2; extra == 'all'
Requires-Dist: timm>=1.0.12; extra == 'all'
Provides-Extra: lightning
Requires-Dist: lightning>=2.4.0; extra == 'lightning'
Provides-Extra: onnx
Requires-Dist: onnx>=1.17.0; extra == 'onnx'
Requires-Dist: onnxruntime>=1.19.2; extra == 'onnx'
Provides-Extra: timm
Requires-Dist: timm>=1.0.12; extra == 'timm'
